fpm_risk_model/__init__.py
fpm_risk_model/accuracy/__init__.py
fpm_risk_model/accuracy/bias.py
fpm_risk_model/accuracy/value_at_risk.py
fpm_risk_model/config.py
fpm_risk_model/cov_estimator.py
fpm_risk_model/dataset/__init__.py
fpm_risk_model/dataset/crypto.py
fpm_risk_model/engine.py
fpm_risk_model/factor_risk_model.py
fpm_risk_model/pipeline/__init__.py
fpm_risk_model/pipeline/portfolio.py
fpm_risk_model/pipeline/returns.py
fpm_risk_model/py.typed
fpm_risk_model/regressor/__init__.py
fpm_risk_model/regressor/ewls.py
fpm_risk_model/regressor/wls.py
fpm_risk_model/risk_model.py
fpm_risk_model/rolling_factor_risk_model.py
fpm_risk_model/rolling_risk_model.py
fpm_risk_model/statistical/__init__.py
fpm_risk_model/statistical/apca.py
fpm_risk_model/statistical/pca.py
factor_pricing_model_risk_model-2023.8.0.dist-info/LICENSE
factor_pricing_model_risk_model-2023.8.0.dist-info/METADATA
factor_pricing_model_risk_model-2023.8.0.dist-info/WHEEL
factor_pricing_model_risk_model-2023.8.0.dist-info/RECORD
