Metadata-Version: 2.1
Name: factor-pricing-model-risk-model
Version: 2023.8.0
Summary: Package to build risk models for factor pricing model
Home-page: https://github.com/factorpricingmodel/factor-pricing-model-risk-model
License: MIT
Author: Factor Pricing Model
Author-email: factor.pricing.model@gmail.com
Requires-Python: >=3.8,<4.0
Classifier: Development Status :: 2 - Pre-Alpha
Classifier: Intended Audience :: Developers
Classifier: License :: OSI Approved :: MIT License
Classifier: Natural Language :: English
Classifier: Operating System :: OS Independent
Classifier: Programming Language :: Python :: 3
Classifier: Programming Language :: Python :: 3.8
Classifier: Programming Language :: Python :: 3.9
Classifier: Programming Language :: Python :: 3.10
Classifier: Programming Language :: Python :: 3.11
Classifier: Programming Language :: Python :: 3.12
Classifier: Topic :: Software Development :: Libraries
Provides-Extra: docs
Requires-Dist: Sphinx (>=5.0,<6.0) ; extra == "docs"
Requires-Dist: insipid-sphinx-theme (>=0.3.6,<0.4.0) ; extra == "docs"
Requires-Dist: myst-parser (>=0.18,<0.19) ; extra == "docs"
Requires-Dist: pandas (>=1.3.5,<3.0.0)
Requires-Dist: pydantic (>=1.10.4,<2.0.0)
Requires-Dist: scikit-learn (>=1.1.3,<2.0.0)
Requires-Dist: tqdm (>=4.64.1,<5.0.0)
Project-URL: Bug Tracker, https://github.com/factorpricingmodel/factor-pricing-model-risk-model/issues
Project-URL: Changelog, https://github.com/factorpricingmodel/factor-pricing-model-risk-model/blob/master/CHANGELOG.md
Project-URL: Documentation, https://factor-pricing-model-risk-model.readthedocs.io
Project-URL: Repository, https://github.com/factorpricingmodel/factor-pricing-model-risk-model
